tc3tools/__init__.py
tc3tools/__main__.py
tc3tools/cli.py
tc3tools/py.typed
tc3tools/converters/__init__.py
tc3tools/converters/st_to_xml.py
tc3tools/converters/xml_to_st.py
tc3tools/core/__init__.py
tc3tools/core/common.py
tc3tools/formatters/__init__.py
tc3tools/formatters/st_formatter.py
tc3tools/formatters/xml_formatter.py
tc3tools-0.1.0.dist-info/METADATA
tc3tools-0.1.0.dist-info/WHEEL
tc3tools-0.1.0.dist-info/entry_points.txt
tc3tools-0.1.0.dist-info/licenses/LICENSE
tc3tools-0.1.0.dist-info/RECORD
