Metadata-Version: 2.4
Name: tc3tools
Version: 0.1.0
Summary: A CLI toolkit for TwinCAT/Beckhoff development workflows - format, lint, and convert Structured Text and TwinCAT XML files
Project-URL: Homepage, https://github.com/BhanuKiranChaluvadi/tctool
Project-URL: Documentation, https://github.com/BhanuKiranChaluvadi/tctool#readme
Project-URL: Repository, https://github.com/BhanuKiranChaluvadi/tctool.git
Project-URL: Issues, https://github.com/BhanuKiranChaluvadi/tctool/issues
Project-URL: Changelog, https://github.com/BhanuKiranChaluvadi/tctool/blob/main/CHANGELOG.md
Author-email: Bhanu Kiran Chaluvadi <bhanukiran.chaluvadi@example.com>
Maintainer-email: Bhanu Kiran Chaluvadi <bhanukiran.chaluvadi@example.com>
License-Expression: MIT
License-File: LICENSE
Keywords: automation,beckhoff,converter,formatter,iec-61131-3,linter,plc,st,structured-text,twincat
Classifier: Development Status :: 4 - Beta
Classifier: Environment :: Console
Classifier: Intended Audience :: Developers
Classifier: License :: OSI Approved :: MIT License
Classifier: Operating System :: OS Independent
Classifier: Programming Language :: Python :: 3
Classifier: Programming Language :: Python :: 3.10
Classifier: Programming Language :: Python :: 3.11
Classifier: Programming Language :: Python :: 3.12
Classifier: Programming Language :: Python :: 3.13
Classifier: Topic :: Software Development :: Build Tools
Classifier: Topic :: Software Development :: Code Generators
Classifier: Topic :: Software Development :: Quality Assurance
Classifier: Typing :: Typed
Requires-Python: >=3.10
Provides-Extra: dev
Requires-Dist: mypy>=1.0; extra == 'dev'
Requires-Dist: pre-commit>=3.0; extra == 'dev'
Requires-Dist: pytest-cov>=4.0; extra == 'dev'
Requires-Dist: pytest>=7.0; extra == 'dev'
Requires-Dist: ruff>=0.4; extra == 'dev'
